nanomongo/__init__.py
nanomongo/document.py
nanomongo/errors.py
nanomongo/field.py
nanomongo/util.py
nanomongo-0.4.1.dist-info/DESCRIPTION.rst
nanomongo-0.4.1.dist-info/METADATA
nanomongo-0.4.1.dist-info/metadata.json
nanomongo-0.4.1.dist-info/RECORD
nanomongo-0.4.1.dist-info/top_level.txt
nanomongo-0.4.1.dist-info/WHEEL
